Gym/__init__.py
Gym/environment.py
Gym/parameter_controller.py
Gym/environments/__init__.py
Gym/environments/ab_program_simulation/__init__.py
Gym/environments/ab_program_simulation/environment.py
Gym/environments/add_multiple_divisible_counting/__init__.py
Gym/environments/add_multiple_divisible_counting/environment.py
Gym/environments/addition_table/__init__.py
Gym/environments/addition_table/environment.py
Gym/environments/almost_complete_graph_cycle_counting/__init__.py
Gym/environments/almost_complete_graph_cycle_counting/environment.py
Gym/environments/and_or_sequence_counting/__init__.py
Gym/environments/and_or_sequence_counting/environment.py
Gym/environments/anti_palindromic_substring_counting/__init__.py
Gym/environments/anti_palindromic_substring_counting/environment.py
Gym/environments/axis_k_center/__init__.py
Gym/environments/axis_k_center/environment.py
Gym/environments/baj_bytecomputer/__init__.py
Gym/environments/baj_bytecomputer/environment.py
Gym/environments/banned_point_superset_path_counting/__init__.py
Gym/environments/banned_point_superset_path_counting/environment.py
Gym/environments/banyan_heart/__init__.py
Gym/environments/banyan_heart/environment.py
Gym/environments/bez_minimalist_security/__init__.py
Gym/environments/bez_minimalist_security/environment.py
Gym/environments/bezout_identity/__init__.py
Gym/environments/bezout_identity/environment.py
Gym/environments/binario/__init__.py
Gym/environments/binario/environment.py
Gym/environments/binario_no_adjacency_requirement/__init__.py
Gym/environments/binario_no_adjacency_requirement/environment.py
Gym/environments/binary_alternation/__init__.py
Gym/environments/binary_alternation/environment.py
Gym/environments/binary_linear_equation_solution_counting/__init__.py
Gym/environments/binary_linear_equation_solution_counting/environment.py
Gym/environments/binary_tree_leaf_num_expectation/__init__.py
Gym/environments/binary_tree_leaf_num_expectation/environment.py
rlve_gym-0.0.1.dist-info/METADATA
rlve_gym-0.0.1.dist-info/WHEEL
rlve_gym-0.0.1.dist-info/top_level.txt
rlve_gym-0.0.1.dist-info/RECORD
