Metadata-Version: 2.4
Name: rlve-gym
Version: 0.0.1
Summary: RLVE Gym environments shim - exposes Gym.environments and Gym.parameter_controllers
Author-email: RLVE Team <zhiyuan1zeng@gmail.com>
License: MIT
Project-URL: Homepage, https://github.com/Zhiyuan-Zeng/RLVE
Requires-Python: >=3.9
